{"resource_state":3,"athlete":{"id":62214940,"resource_state":1},"name":"Zwift - Cucumber in New York","distance":41474,"moving_time":5407,"elapsed_time":5407,"total_elevation_gain":695,"type":"VirtualRide","sport_type":"VirtualRide","id":9450997559,"start_date":"2023-07-14T16:14:27Z","start_date_local":"2023-07-14T18:14:27Z","timezone":"(GMT+01:00) Europe\/Brussels","utc_offset":7200,"location_city":null,"location_state":null,"location_country":null,"achievement_count":13,"kudos_count":5,"comment_count":0,"athlete_count":1,"photo_count":0,"map":{"id":"a9450997559","polyline":"}s{wFxlmbM~DrD\\Vj@XlCr@pBb@d@BtAKV@VJPRNV`AfCZp@`@h@b@b@d@^b@VPD\\DZ@VCt@QxAi@TGTARBZHdBv@^V^b@Tb@hAnCh@|@f@b@lC`Br@t@r@jAHb@@d@Kx@_AtCMh@El@?VFl@HVXh@f@v@Z`@h@h@v@j@xA|@rAt@bBv@XPTVTr@Dd@Ez@Ox@m@`Cg@tA[l@WT[FMAMG[UoBeCyAyA{DqC_@]m@o@a@o@a@kAGo@Be@HYHGTEVBvCf@T?VGb@WbByA\\W^Ix@BXIZ[d@{@RKJ?HDl@^f@n@N^BPAb@Gd@_@jAwBnEUp@Or@Cd@@b@L|@VrAD^CTENILgAp@SRKRo@hBUx@OdAAr@F^HTR\\Z\\dAv@lBfA~@\\v@Jl@CXGPK`@_@b@m@x@wAZw@nAcErCuK~@cDp@kBnBeEl@gBHc@Bc@Ce@Ka@O[g@m@{@q@mC}Am@WYI]C]?_@LW\\e@dAYZ]OW_@cAkB]Sc@?a@Pa@XW`@Ub@aBnEc@t@UN[@y@?[LYPcBxAWP]J]AaBWaAS[QIe@@e@RmCh@oCFq@@YCWKm@{@gC[mACQ@SNe@Xa@nA}A\\m@H]B[Is@Mc@O]Ya@aAgAgAaA_CkBkDgCgCeBkD{B{CkByC_B{@a@iAa@cA[s@Mm@G_@B}@TaAd@e@^_@j@Ul@Qp@iBnIW`AGLWRu@VeAPy@Dk@AgAMuAWuDy@aBa@sAg@oCmAiAq@cBiAkYwS_Au@uCqCeA{@aAo@i@Se@C[@gCHcD^qBN}@BaAGm@Om@WeDcBiEgC{GiEq@g@Q]Ma@Gc@?e@\\uBP_ADQN[XYZOdD_@|@QTATDl@VTNh@f@b@t@Xz@r@fDL\\PZl@d@~Ap@PPLTh@vAl@hC`@rARh@V`@l@f@~DrB|BpAz@l@Z\\PXv@tBT`@LLNDr@HzBJt@Ff@LTP`@l@^~@Lf@^tB\\jAPZp@fA^h@d@d@|@n@z@`@`A\\n@Hl@Az@MrC}@n@MXAXBh@NVL`@Xx@v@bCtCPXNZZpAJRPPRJVFV@V?xBQV@n@RTLh@d@nBxBhGnHv@nAlCbFxBzBf@XTFTB`ACjBQhBE|@Bd@JPHNLJNlArDb@`A\\f@f@\\jAn@lCfAfCx@d@Tf@^v@v@xAjBfCzDj@p@rArAv@n@h@^^N^Jb@@NCz@e@\\]Xc@|AeCVk@f@{A`@{ATgAFgACo@GSUg@[[]SaBu@oAq@uAy@q@e@_AaAaA_BKUESEk@Bg@Lw@~@sCHa@De@AQEe@EQQ_@_@k@u@{@w@i@eBcAe@e@i@_AkAuC]g@WUg@Y}Ao@a@IQ?g@HsAf@cAVW@YAWEWKm@c@g@e@c@i@[m@eAsCS_@KK[OMAm@?aAFcAOqAYqBk@o@Wc@YkGyFkB}A}EoDc@a@UYWu@U{@Km@Im@?q@V{C?k@Cg@Ie@Mc@KKa@a@e@[iVaPoDwBy@Yg@IoBAuBOW?WDo@TuA|@UJUFW@UAUIi@U}@g@}@m@g@c@gAkAqCsDi@m@_@Wa@MQ?mCL_@@_@CcBW_@I_@Q{@w@k@q@MWk@kBOWSQYGYBWJUTO\\K`@?d@Dd@Jb@L`@t@zADd@Cd@M^UVYLYBWKe@c@cBqBa@_@s@a@gAg@q@]]YKOGSG_ABi@BSzA}FRo@PW\\[`Ac@x@Yn@MZEZ?pBPd@CVIRUN[z@iDPk@RYNKNEP?TBPFv@b@jBtA`CrBtH|E~AhA\\\\\\d@Tl@DX?\\Ov@u@bCE\\A^H\\NVf@d@rAv@PN\\b@HT@TATI^c@zAGl@@TDVLVPVvAnA`FzD~FxDtAx@fB|@tAj@hLpDdBn@bAf@d@Z^`@Xf@HXHf@Bj@A`@IpA[rCGTIRUZKH[F_@AcB]WAWBST]t@K^G^A`@D`@J\\RTxAx@d@^j@t@x@tAN^Hf@AxABd@Nf@TRVLt@RpCb@t@Fv@Cx@Kx@Sb@QPMRk@XgAhBgIRs@Xm@`@e@RMj@YdA]XCX?lAPp@RhA`@|Ap@tC~AnEnCxEbDnDhCdDlCfBbBj@t@Vn@HZB^A^K^a@l@_BlBOZG^?NF`@^vAp@lBJh@BT?TEn@m@dDSrC?VBVJPNJ`@Ln@LhBV^?RGRMrBgBZQZI|@@VITUXe@bBsE\\s@JOXU`@UNCL?LBRPpAbCPRLFD@LCRONW^}@RYXI^?n@Hl@VrCbBx@n@`@d@R^DPDR?f@Mt@Qn@[z@eCnFq@hBgAxDoClK{@rCg@dAq@jAm@p@]R_@Ha@@_@E{@Uw@_@sAw@w@k@Y[W_@Og@Ck@Dk@VoA|@gCRYhAs@RYDc@Ee@]mBGe@?i@Fg@ZiAd@gAnAiC`@iAJg@@g@Ge@Q]UYk@g@WOWAUNo@bAQPWFu@A[DYNYR_BvAYN]F_@CcCa@a@C[PKb@Cf@Db@H`@L^P\\f@t@dAdAvDnCXVjAhAnB`CJ\\B^A^GXKVa@^u@^QDg@Ec@Qs@a@oAeA_A_A{@gAeBmCiA{A_AiAm@i@a@Yi@U{Bw@eCaAkAm@c@Y_@c@[o@Ys@{@kCOWUQUKUGWCm@CmBDiCRc@@c@Gm@[e@e@uA}Ae@y@eBiDaAyAcHiIaAeAw@s@_@Si@MU?oCP]C[MQQIMWkAQe@c@o@_BiB_AaAm@e@u@[e@IS?c@Be@HiC|@k@Jm@FWAk@Iy@[o@[y@i@m@m@e@m@y@uAQ_@Uw@c@aCOk@a@_A_@c@QMSIi@Ki@EcCIk@IQOOS}@_CWc@Y]_@WaAm@kBeAaDaBg@[a@i@Ys@c@uAc@sBq@oB?_@J[fAqB^eAReABcAI}@Uu@m@uA{@yASk@Kg@Eo@Bk@BKFKROXIJ?j@Dj@Jl@D`@AnCMPBPF^Tx@|@lClD|@`An@h@hAt@t@`@t@XZ@j@I\\MnA{@h@Sf@IhCRvBDh@J~@b@nCbBrSbNnBrAn@h@JTNn@Ft@Ct@UfC@t@Ft@Ln@j@fBV^h@h@jHnFfCvBjDbDp@^b@PpBf@fB^l@DjAIX?XHVRPXfAvCb@t@f@j@h@d@h@\\RHf@DP?`@El@MvAi@\\IP?b@FjAd@n@Z`@\\^j@nAzCd@x@NN^ZxBrAb@Zx@dAVd@HRFn@Cp@Ol@{@hCKr@CZDx@HXJX|@xA`@b@`@^p@h@pAv@|Az@~Ar@^TLLHRRh@Bl@IhA]zAk@lB]|@Ub@MLOHQBQAOIa@[eBwBsAwAgE}CcAcAg@u@Yy@Mi@AY@]H]HIXElDj@V?VGd@YrAmAh@_@\\Kx@@ZGZ[^s@RQLAJBf@Xb@f@T^FR@h@CTKh@_@bAoB`EUn@Qz@Cd@@f@Hj@\\jBBTCTELKNgAp@ONMTi@zA]pAKr@Ct@D`@JV`@n@|@t@hBfA`Ab@z@Rl@@VCXKVO`@a@jAmB\\w@jAyDzCkLlAcE`@eAlBcE`@aAVeAFc@?e@Ic@O]g@q@aAw@_DgBw@W_@C_@@_@PW`@g@hA_@J[[cAmB[]c@Ic@La@T[^Wd@cArCo@|ASXURYBy@?]Hs@h@iAbAYP[J]@cBW_AS]QKa@@g@HiAHcAl@mDBs@AYKm@_AkCYmAASDSPc@jBaCNWJYD[?]Km@Uq@e@u@gBgB{D}C}DsCaEoCwEuCiDiBmBw@","resource_state":3,"summary_polyline":"}s{wFxlmbMhGdF~FvAjDD~BdFnCdCbBHzDeAtCdA~@z@hCpFtFjEr@dCyAxFJjCtCxD`JfFb@zBaBhHwAzAsKqJ_DiDa@{AJsAvFXnDoCnBMtAcBjBtARp@IhA}D`Kd@pGwBvBwAzFF`Ad@|@zDlCxDh@tCaDlIkYxE}L?iAm@uAuFsDmCIwA~ByB{CaAS{AlAwBrFy@dAqBNsDhCaEm@[QGkAfAiJkBmHPy@fCmDLy@WwAkBgCgEmDiS_NmHeDsD_@uBx@eAjAiDpN_@`@sEn@qJeBwKwEw[oU}IsHyBUyNx@wGoCwOyJg@cBn@{Ef@_Az@]`Fm@xAl@lA|AlB|GlD~BdD`KfLzGhC|ErHbA`AlBjAhFhCrDjFxBlH{AtB^~EfFzAlDlFDnBfAxJhLdErHxBzBrAd@vG[tBXjDzHvMdGdIpKtDbDrBXrBgB|CmGv@cDBwBy@wAwI{EaCaDS}BvAmFGoBgBgCwDeCiDwGuD}A{GbAqC_CaCmF}EYwGwBoScQcAmEVyFg@}Ba^wU_Ju@sDdByAAmEoCcHeIaGAcDs@gBiBiA{Cm@YgAd@[~@PnBhAbDQdAiAh@cEaEkEaCWy@BgB`BmGn@iAbEwAtEDlCgHhB@fVpQZdBmAxFXt@tDfDu@zEt@fBxHfGhJ|F|SlH`DzBf@fCo@|GgA`AsD]q@jAU`BP~@rCnBdBjCXfA@~Bd@z@tGlAnEu@vEkPfDkB`CLnFtBdL`HjMlJ`DfDb@jCeDvFhBvHgA~J^lAzEr@vDoCpBQpDcIvA_An@TpB~Cf@QbAoBt@K`Bb@`EfCfAbBGpB_FxLaIlX_B|B}@\\}BYgDkBmAsAM_CtAwEpBgBe@gGb@qBvC{GLoAo@}A{Ay@wAdBiBJmDjC_GOInBz@zBhNrML|Ac@bAyAr@}Aa@aEmDiIuK}LqFwD}HqB[{GZqAc@{BcCcEqHoJ{KwBsAiFAqAcDeFoFaCe@sH|AmDqAoDkE{AeGaAcBiH}@qCeFyLsHsCmJzBkGLgC{CyHIoC`Ae@zIRdHbIdFzCfAG~DgB`GXhBn@b]dUb@zBWrF`AlE`TtQnHxBlDDtCzFnCxBzA?tDaAvD|A~CjGlEzCzA~BB`BwAjFVhCpClDpIvEn@xB}AfHi@lAo@Z}FwFuGkFcAcCPkBpF^hDiCrBQnAaB`AZ`AzAMhBwDhJd@xGiB~Ak@rAu@bDFbB~BdCvElBlB_@rByClIwY|DmJRmBYaAiBiBwE_C_BN_AjB_@J{BgDc@IaBbAuDdIqBLsDjC_F{@?sCz@eHiBuH~CkFDy@a@_BmC}CyJqHqTgM"},"trainer":false,"commute":false,"manual":false,"private":false,"visibility":"everyone","flagged":false,"gear_id":"b12659743","start_latlng":[40.78,-73.97],"end_latlng":[40.78,-73.96],"average_speed":7.67,"max_speed":20.688,"average_cadence":90.3,"average_watts":177.9,"max_watts":342,"weighted_average_watts":188,"kilojoules":962,"device_watts":true,"has_heartrate":true,"average_heartrate":154.9,"max_heartrate":179,"heartrate_opt_out":false,"display_hide_heartrate_option":true,"elev_high":132.8,"elev_low":4.6,"upload_id":10136189863,"upload_id_str":"10136189863","external_id":"zwift-activity-1387832550235308080.fit","from_accepted_tag":false,"pr_count":7,"total_photo_count":4,"has_kudoed":false,"description":null,"calories":919,"perceived_exertion":null,"prefer_perceived_exertion":null,"segment_efforts":[{"id":3114991729808487868,"resource_state":2,"name":"Everything Bagel","activity":{"id":9450997559,"resource_state":1},"athlete":{"id":62214940,"resource_state":1},"elapsed_time":4366,"moving_time":4366,"start_date":"2023-07-14T16:15:31Z","start_date_local":"2023-07-14T18:15:31Z","distance":34220.4,"start_index":41,"end_index":4407,"average_cadence":90.2,"device_watts":true,"average_watts":179.7,"average_heartrate":155.7,"max_heartrate":179,"segment":{"id":19141223,"resource_state":2,"name":"Everything Bagel","activity_type":"VirtualRide","distance":34220.4,"average_grade":0,"maximum_grade":16.6,"elevation_high":132.8,"elevation_low":4.6,"start_latlng":[40.776848,-73.967187],"end_latlng":[40.776867,-73.967181],"elevation_profile":null,"climb_category":0,"city":null,"state":null,"country":null,"private":false,"hazardous":false,"starred":false},"pr_rank":null,"achievements":[],"hidden":false},{"id":3114991729811332540,"resource_state":2,"name":"NYC KOM Reverse from Ground Level","activity":{"id":9450997559,"resource_state":1},"athlete":{"id":62214940,"resource_state":1},"elapsed_time":641,"moving_time":641,"start_date":"2023-07-14T16:19:36Z","start_date_local":"2023-07-14T18:19:36Z","distance":2087.4,"start_index":286,"end_index":927,"average_cadence":95.4,"device_watts":true,"average_watts":150.7,"average_heartrate":142,"max_heartrate":167,"segment":{"id":27207759,"resource_state":2,"name":"NYC KOM Reverse from Ground Level","activity_type":"VirtualRide","distance":2087.4,"average_grade":5.4,"maximum_grade":15,"elevation_high":132.8,"elevation_low":20.4,"start_latlng":[40.768445,-73.978801],"end_latlng":[40.765331,-73.978871],"elevation_profile":null,"climb_category":1,"city":"New York","state":"New York","country":"United States","private":false,"hazardous":false,"starred":false},"pr_rank":2,"achievements":[{"type_id":3,"type":"pr","rank":2}],"hidden":false},{"id":3114991729810249148,"resource_state":2,"name":"NYC KOM Reverse","activity":{"id":9450997559,"resource_state":1},"athlete":{"id":62214940,"resource_state":1},"elapsed_time":356,"moving_time":356,"start_date":"2023-07-14T16:24:21Z","start_date_local":"2023-07-14T18:24:21Z","distance":1145.1,"start_index":571,"end_index":927,"average_cadence":97,"device_watts":true,"average_watts":163.2,"average_heartrate":147.5,"max_heartrate":167,"segment":{"id":19141092,"resource_state":2,"name":"NYC KOM Reverse","activity_type":"VirtualRide","distance":1145.1,"average_grade":5.9,"maximum_grade":15.6,"elevation_high":132.8,"elevation_low":65.2,"start_latlng":[40.767345,-73.97525],"end_latlng":[40.765353,-73.978897],"elevation_profile":null,"climb_category":0,"city":"New York","state":"New York","country":"United States","private":false,"hazardous":false,"starred":false},"pr_rank":null,"achievements":[],"hidden":false},{"id":3114991729810447804,"resource_state":2,"name":"NYC KOM Descent","activity":{"id":9450997559,"resource_state":1},"athlete":{"id":62214940,"resource_state":1},"elapsed_time":86,"moving_time":86,"start_date":"2023-07-14T16:30:17Z","start_date_local":"2023-07-14T18:30:17Z","distance":1370,"start_index":927,"end_index":1013,"average_cadence":92.6,"device_watts":true,"average_watts":180.5,"average_heartrate":167.1,"max_heartrate":176,"segment":{"id":27207768,"resource_state":2,"name":"NYC KOM Descent","activity_type":"VirtualRide","distance":1370,"average_grade":-6.4,"maximum_grade":1.1,"elevation_high":132.6,"elevation_low":44.6,"start_latlng":[40.765331,-73.978871],"end_latlng":[40.77028,-73.975443],"elevation_profile":null,"climb_category":0,"city":"New York","state":"New York","country":"United States","private":false,"hazardous":false,"starred":false},"pr_rank":2,"achievements":[{"type_id":3,"type":"pr","rank":2}],"hidden":false},{"id":3114991729810732476,"resource_state":2,"name":"Three Sisters - Fulgaz","activity":{"id":9450997559,"resource_state":1},"athlete":{"id":62214940,"resource_state":1},"elapsed_time":290,"moving_time":290,"start_date":"2023-07-14T16:40:12Z","start_date_local":"2023-07-14T18:40:12Z","distance":2613.5,"start_index":1522,"end_index":1812,"average_cadence":89,"device_watts":true,"average_watts":179.3,"average_heartrate":160.3,"max_heartrate":168,"segment":{"id":30349583,"resource_state":2,"name":"Three Sisters - Fulgaz","activity_type":"VirtualRide","distance":2613.5,"average_grade":0,"maximum_grade":5.7,"elevation_high":40,"elevation_low":18.6,"start_latlng":[40.794307,-73.9597],"end_latlng":[40.775591,-73.974162],"elevation_profile":null,"climb_category":0,"city":"New York","state":"New York","country":"United States","private":false,"hazardous":false,"starred":false},"pr_rank":2,"achievements":[{"type_id":3,"type":"pr","rank":2}],"hidden":false},{"id":3114991729808796092,"resource_state":2,"name":"ODZ Kidney Kicker","activity":{"id":9450997559,"resource_state":1},"athlete":{"id":62214940,"resource_state":1},"elapsed_time":53,"moving_time":53,"start_date":"2023-07-14T16:45:01Z","start_date_local":"2023-07-14T18:45:01Z","distance":378.5,"start_index":1811,"end_index":1864,"average_cadence":76.5,"device_watts":true,"average_watts":200.1,"average_heartrate":154.8,"max_heartrate":158,"segment":{"id":19192732,"resource_state":2,"name":"ODZ Kidney Kicker","activity_type":"VirtualRide","distance":378.5,"average_grade":3,"maximum_grade":6.3,"elevation_high":31.4,"elevation_low":20,"start_latlng":[40.775719,-73.974053],"end_latlng":[40.773088,-73.976478],"elevation_profile":null,"climb_category":0,"city":"New York","state":"New York","country":"United States","private":false,"hazardous":false,"starred":false},"pr_rank":2,"achievements":[{"type_id":3,"type":"pr","rank":2}],"hidden":false},{"id":3114991729810166204,"resource_state":2,"name":"East Side - Fulgaz","activity":{"id":9450997559,"resource_state":1},"athlete":{"id":62214940,"resource_state":1},"elapsed_time":366,"moving_time":366,"start_date":"2023-07-14T16:49:16Z","start_date_local":"2023-07-14T18:49:16Z","distance":3632.7,"start_index":2066,"end_index":2432,"average_cadence":76.4,"device_watts":true,"average_watts":194.6,"average_heartrate":161.9,"max_heartrate":164,"segment":{"id":30349547,"resource_state":2,"name":"East Side - Fulgaz","activity_type":"VirtualRide","distance":3632.7,"average_grade":-0.5,"maximum_grade":6,"elevation_high":35.8,"elevation_low":8.2,"start_latlng":[40.773024,-73.968846],"end_latlng":[40.797781,-73.954339],"elevation_profile":null,"climb_category":0,"city":"New York","state":"New York","country":"United States","private":false,"hazardous":false,"starred":false},"pr_rank":1,"achievements":[{"type_id":3,"type":"pr","rank":1}],"hidden":false},{"id":3114991729810430396,"resource_state":2,"name":"East Side Sky Loop Climb","activity":{"id":9450997559,"resource_state":1},"athlete":{"id":62214940,"resource_state":1},"elapsed_time":193,"moving_time":193,"start_date":"2023-07-14T16:55:48Z","start_date_local":"2023-07-14T18:55:48Z","distance":739.4,"start_index":2458,"end_index":2651,"average_cadence":88.7,"device_watts":true,"average_watts":186,"average_heartrate":157.9,"max_heartrate":165,"segment":{"id":27207860,"resource_state":2,"name":"East Side Sky Loop Climb","activity_type":"VirtualRide","distance":739.4,"average_grade":5.8,"maximum_grade":9.7,"elevation_high":51,"elevation_low":8,"start_latlng":[40.797646,-73.951973],"end_latlng":[40.792188,-73.951249],"elevation_profile":null,"climb_category":0,"city":"New York","state":"New York","country":"United States","private":false,"hazardous":false,"starred":false},"pr_rank":1,"achievements":[{"type_id":3,"type":"pr","rank":1}],"hidden":false},{"id":3114991729808836028,"resource_state":2,"name":"NYC KOM","activity":{"id":9450997559,"resource_state":1},"athlete":{"id":62214940,"resource_state":1},"elapsed_time":411,"moving_time":411,"start_date":"2023-07-14T17:07:09Z","start_date_local":"2023-07-14T19:07:09Z","distance":1367.3,"start_index":3139,"end_index":3550,"average_cadence":91.4,"device_watts":true,"average_watts":183.1,"average_heartrate":157.9,"max_heartrate":179,"segment":{"id":19141090,"resource_state":2,"name":"NYC KOM","activity_type":"VirtualRide","distance":1367.3,"average_grade":6.4,"maximum_grade":17.9,"elevation_high":132.6,"elevation_low":44.8,"start_latlng":[40.770296,-73.975528],"end_latlng":[40.765398,-73.978838],"elevation_profile":null,"climb_category":1,"city":"New York","state":"New York","country":"United States","private":false,"hazardous":false,"starred":false},"pr_rank":null,"achievements":[],"hidden":false},{"id":3114991729811340732,"resource_state":2,"name":"NYC KOM Reverse Descent","activity":{"id":9450997559,"resource_state":1},"athlete":{"id":62214940,"resource_state":1},"elapsed_time":77,"moving_time":77,"start_date":"2023-07-14T17:14:00Z","start_date_local":"2023-07-14T19:14:00Z","distance":1134.8,"start_index":3550,"end_index":3627,"average_cadence":90.7,"device_watts":true,"average_watts":210,"average_heartrate":163.8,"max_heartrate":165,"segment":{"id":27207796,"resource_state":2,"name":"NYC KOM Reverse Descent","activity_type":"VirtualRide","distance":1134.8,"average_grade":-5.9,"maximum_grade":1.7,"elevation_high":132.8,"elevation_low":65.2,"start_latlng":[40.765398,-73.978838],"end_latlng":[40.7673,-73.975314],"elevation_profile":null,"climb_category":0,"city":"New York","state":"New York","country":"United States","private":false,"hazardous":false,"starred":false},"pr_rank":1,"achievements":[{"type_id":3,"type":"pr","rank":1}],"hidden":false},{"id":3114991729812041148,"resource_state":2,"name":"NYC KOM Reverse from Ground Level","activity":{"id":9450997559,"resource_state":1},"athlete":{"id":62214940,"resource_state":1},"elapsed_time":494,"moving_time":494,"start_date":"2023-07-14T17:31:14Z","start_date_local":"2023-07-14T19:31:14Z","distance":2087.4,"start_index":4584,"end_index":5078,"average_cadence":88.8,"device_watts":true,"average_watts":199,"average_heartrate":158.8,"max_heartrate":166,"segment":{"id":27207759,"resource_state":2,"name":"NYC KOM Reverse from Ground Level","activity_type":"VirtualRide","distance":2087.4,"average_grade":5.4,"maximum_grade":15,"elevation_high":132.8,"elevation_low":20.4,"start_latlng":[40.768445,-73.978801],"end_latlng":[40.765331,-73.978871],"elevation_profile":null,"climb_category":1,"city":"New York","state":"New York","country":"United States","private":false,"hazardous":false,"starred":false},"pr_rank":1,"achievements":[{"type_id":3,"type":"pr","rank":1}],"hidden":false},{"id":3114991718938786386,"resource_state":2,"name":"NYC KOM Reverse","activity":{"id":9450997559,"resource_state":1},"athlete":{"id":62214940,"resource_state":1},"elapsed_time":288,"moving_time":288,"start_date":"2023-07-14T17:34:40Z","start_date_local":"2023-07-14T19:34:40Z","distance":1145.1,"start_index":4790,"end_index":5078,"average_cadence":90.4,"device_watts":true,"average_watts":201.5,"average_heartrate":159.8,"max_heartrate":165,"segment":{"id":19141092,"resource_state":2,"name":"NYC KOM Reverse","activity_type":"VirtualRide","distance":1145.1,"average_grade":5.9,"maximum_grade":15.6,"elevation_high":132.8,"elevation_low":65.2,"start_latlng":[40.767345,-73.97525],"end_latlng":[40.765353,-73.978897],"elevation_profile":null,"climb_category":0,"city":"New York","state":"New York","country":"United States","private":false,"hazardous":false,"starred":false},"pr_rank":1,"achievements":[{"type_id":3,"type":"pr","rank":1}],"hidden":false},{"id":3114991718936969810,"resource_state":2,"name":"NYC KOM Descent","activity":{"id":9450997559,"resource_state":1},"athlete":{"id":62214940,"resource_state":1},"elapsed_time":84,"moving_time":84,"start_date":"2023-07-14T17:39:28Z","start_date_local":"2023-07-14T19:39:28Z","distance":1370,"start_index":5078,"end_index":5162,"average_cadence":98,"device_watts":true,"average_watts":221.6,"average_heartrate":170,"max_heartrate":175,"segment":{"id":27207768,"resource_state":2,"name":"NYC KOM Descent","activity_type":"VirtualRide","distance":1370,"average_grade":-6.4,"maximum_grade":1.1,"elevation_high":132.6,"elevation_low":44.6,"start_latlng":[40.765331,-73.978871],"end_latlng":[40.77028,-73.975443],"elevation_profile":null,"climb_category":0,"city":"New York","state":"New York","country":"United States","private":false,"hazardous":false,"starred":false},"pr_rank":1,"achievements":[{"type_id":3,"type":"pr","rank":1}],"hidden":false}],"splits_metric":[{"distance":1002,"elapsed_time":165,"elevation_difference":-6.4,"moving_time":165,"split":1,"average_speed":6.07,"average_grade_adjusted_speed":null,"average_heartrate":111.24848484848485,"pace_zone":0},{"distance":1006,"elapsed_time":119,"elevation_difference":-6.6,"moving_time":119,"split":2,"average_speed":8.45,"average_grade_adjusted_speed":null,"average_heartrate":123.08403361344538,"pace_zone":0},{"distance":996.3,"elapsed_time":289,"elevation_difference":44.4,"moving_time":289,"split":3,"average_speed":3.45,"average_grade_adjusted_speed":null,"average_heartrate":134.24567474048442,"pace_zone":0},{"distance":996,"elapsed_time":282,"elevation_difference":50.6,"moving_time":282,"split":4,"average_speed":3.53,"average_grade_adjusted_speed":null,"average_heartrate":147.8581560283688,"pace_zone":0},{"distance":1001,"elapsed_time":143,"elevation_difference":-22,"moving_time":143,"split":5,"average_speed":7,"average_grade_adjusted_speed":null,"average_heartrate":153.4055944055944,"pace_zone":0},{"distance":1007.2,"elapsed_time":62,"elevation_difference":-51.4,"moving_time":62,"split":6,"average_speed":16.25,"average_grade_adjusted_speed":null,"average_heartrate":155.11290322580646,"pace_zone":0},{"distance":996.1,"elapsed_time":109,"elevation_difference":1,"moving_time":109,"split":7,"average_speed":9.14,"average_grade_adjusted_speed":null,"average_heartrate":145.72477064220183,"pace_zone":0},{"distance":998.1,"elapsed_time":137,"elevation_difference":18.6,"moving_time":137,"split":8,"average_speed":7.29,"average_grade_adjusted_speed":null,"average_heartrate":162.32116788321167,"pace_zone":0},{"distance":997.5,"elapsed_time":109,"elevation_difference":-0.4,"moving_time":109,"split":9,"average_speed":9.15,"average_grade_adjusted_speed":null,"average_heartrate":163.56880733944953,"pace_zone":0},{"distance":1007,"elapsed_time":83,"elevation_difference":-24.6,"moving_time":83,"split":10,"average_speed":12.13,"average_grade_adjusted_speed":null,"average_heartrate":164.04819277108433,"pace_zone":0},{"distance":996.1,"elapsed_time":112,"elevation_difference":-0.8,"moving_time":112,"split":11,"average_speed":8.89,"average_grade_adjusted_speed":null,"average_heartrate":165.66071428571428,"pace_zone":0},{"distance":996.7,"elapsed_time":120,"elevation_difference":7.8,"moving_time":120,"split":12,"average_speed":8.31,"average_grade_adjusted_speed":null,"average_heartrate":164.1,"pace_zone":0},{"distance":1006.4,"elapsed_time":91,"elevation_difference":-24,"moving_time":91,"split":13,"average_speed":11.06,"average_grade_adjusted_speed":null,"average_heartrate":153.3186813186813,"pace_zone":0},{"distance":995.9,"elapsed_time":108,"elevation_difference":3.6,"moving_time":108,"split":14,"average_speed":9.22,"average_grade_adjusted_speed":null,"average_heartrate":155.53703703703704,"pace_zone":0},{"distance":1001.2,"elapsed_time":101,"elevation_difference":0.4,"moving_time":101,"split":15,"average_speed":9.91,"average_grade_adjusted_speed":null,"average_heartrate":160.15841584158414,"pace_zone":0},{"distance":998.5,"elapsed_time":113,"elevation_difference":5.2,"moving_time":113,"split":16,"average_speed":8.84,"average_grade_adjusted_speed":null,"average_heartrate":160.99115044247787,"pace_zone":0},{"distance":999,"elapsed_time":125,"elevation_difference":10.6,"moving_time":125,"split":17,"average_speed":7.99,"average_grade_adjusted_speed":null,"average_heartrate":162.456,"pace_zone":0},{"distance":1002.3,"elapsed_time":91,"elevation_difference":-15.4,"moving_time":91,"split":18,"average_speed":11.01,"average_grade_adjusted_speed":null,"average_heartrate":162.3956043956044,"pace_zone":0},{"distance":1004.6,"elapsed_time":84,"elevation_difference":-19.6,"moving_time":84,"split":19,"average_speed":11.96,"average_grade_adjusted_speed":null,"average_heartrate":161.08333333333334,"pace_zone":0},{"distance":992.5,"elapsed_time":211,"elevation_difference":43,"moving_time":211,"split":20,"average_speed":4.7,"average_grade_adjusted_speed":null,"average_heartrate":157.1990521327014,"pace_zone":0},{"distance":1007.8,"elapsed_time":133,"elevation_difference":7.4,"moving_time":133,"split":21,"average_speed":7.58,"average_grade_adjusted_speed":null,"average_heartrate":165.406015037594,"pace_zone":0},{"distance":1000.9,"elapsed_time":111,"elevation_difference":4.4,"moving_time":111,"split":22,"average_speed":9.02,"average_grade_adjusted_speed":null,"average_heartrate":169.83783783783784,"pace_zone":0},{"distance":994.7,"elapsed_time":111,"elevation_difference":-3.8,"moving_time":111,"split":23,"average_speed":8.96,"average_grade_adjusted_speed":null,"average_heartrate":167.6036036036036,"pace_zone":0},{"distance":1000.9,"elapsed_time":85,"elevation_difference":-14,"moving_time":85,"split":24,"average_speed":11.78,"average_grade_adjusted_speed":null,"average_heartrate":165.96470588235294,"pace_zone":0},{"distance":1001.3,"elapsed_time":183,"elevation_difference":22.8,"moving_time":183,"split":25,"average_speed":5.47,"average_grade_adjusted_speed":null,"average_heartrate":159.07103825136613,"pace_zone":0},{"distance":998.1,"elapsed_time":289,"elevation_difference":66.4,"moving_time":289,"split":26,"average_speed":3.45,"average_grade_adjusted_speed":null,"average_heartrate":158.67820069204151,"pace_zone":0},{"distance":1003.4,"elapsed_time":75,"elevation_difference":-55,"moving_time":75,"split":27,"average_speed":13.38,"average_grade_adjusted_speed":null,"average_heartrate":163.8,"pace_zone":0},{"distance":1006.1,"elapsed_time":61,"elevation_difference":-52.8,"moving_time":61,"split":28,"average_speed":16.49,"average_grade_adjusted_speed":null,"average_heartrate":164.85245901639345,"pace_zone":0},{"distance":995.8,"elapsed_time":102,"elevation_difference":1.6,"moving_time":102,"split":29,"average_speed":9.76,"average_grade_adjusted_speed":null,"average_heartrate":165.14705882352942,"pace_zone":0},{"distance":995.6,"elapsed_time":111,"elevation_difference":7.8,"moving_time":111,"split":30,"average_speed":8.97,"average_grade_adjusted_speed":null,"average_heartrate":161.19819819819818,"pace_zone":0},{"distance":1001.6,"elapsed_time":137,"elevation_difference":9.2,"moving_time":137,"split":31,"average_speed":7.31,"average_grade_adjusted_speed":null,"average_heartrate":160.04379562043795,"pace_zone":0},{"distance":993.5,"elapsed_time":84,"elevation_difference":-19.6,"moving_time":84,"split":32,"average_speed":11.83,"average_grade_adjusted_speed":null,"average_heartrate":155.13095238095238,"pace_zone":0},{"distance":1004.6,"elapsed_time":118,"elevation_difference":10.2,"moving_time":118,"split":33,"average_speed":8.51,"average_grade_adjusted_speed":null,"average_heartrate":152.9322033898305,"pace_zone":0},{"distance":1001.9,"elapsed_time":116,"elevation_difference":3.4,"moving_time":116,"split":34,"average_speed":8.64,"average_grade_adjusted_speed":null,"average_heartrate":162.17241379310346,"pace_zone":0},{"distance":995.3,"elapsed_time":85,"elevation_difference":-19.4,"moving_time":85,"split":35,"average_speed":11.71,"average_grade_adjusted_speed":null,"average_heartrate":155.43529411764706,"pace_zone":0},{"distance":1001.4,"elapsed_time":104,"elevation_difference":4,"moving_time":104,"split":36,"average_speed":9.63,"average_grade_adjusted_speed":null,"average_heartrate":161.59615384615384,"pace_zone":0},{"distance":1001.8,"elapsed_time":146,"elevation_difference":22.8,"moving_time":146,"split":37,"average_speed":6.86,"average_grade_adjusted_speed":null,"average_heartrate":161.2123287671233,"pace_zone":0},{"distance":996,"elapsed_time":230,"elevation_difference":52.6,"moving_time":230,"split":38,"average_speed":4.33,"average_grade_adjusted_speed":null,"average_heartrate":159.7086956521739,"pace_zone":0},{"distance":1002.4,"elapsed_time":195,"elevation_difference":12.6,"moving_time":195,"split":39,"average_speed":5.14,"average_grade_adjusted_speed":null,"average_heartrate":158.82564102564103,"pace_zone":0},{"distance":997.4,"elapsed_time":58,"elevation_difference":-68.4,"moving_time":58,"split":40,"average_speed":17.2,"average_grade_adjusted_speed":null,"average_heartrate":170.3448275862069,"pace_zone":0},{"distance":1003.8,"elapsed_time":115,"elevation_difference":2.6,"moving_time":115,"split":41,"average_speed":8.73,"average_grade_adjusted_speed":null,"average_heartrate":141.81739130434784,"pace_zone":0},{"distance":471.3,"elapsed_time":104,"elevation_difference":6.8,"moving_time":104,"split":42,"average_speed":4.53,"average_grade_adjusted_speed":null,"average_heartrate":125.2156862745098,"pace_zone":0}],"splits_standard":[{"distance":1614.1,"elapsed_time":237,"elevation_difference":-14.8,"moving_time":237,"split":1,"average_speed":6.81,"average_grade_adjusted_speed":null,"average_heartrate":114.37552742616033,"pace_zone":0},{"distance":1608.5,"elapsed_time":368,"elevation_difference":49.2,"moving_time":368,"split":2,"average_speed":4.37,"average_grade_adjusted_speed":null,"average_heartrate":133.3641304347826,"pace_zone":0},{"distance":1614.4,"elapsed_time":381,"elevation_difference":40.2,"moving_time":381,"split":3,"average_speed":4.24,"average_grade_adjusted_speed":null,"average_heartrate":150.10498687664042,"pace_zone":0},{"distance":1601.3,"elapsed_time":123,"elevation_difference":-65.6,"moving_time":123,"split":4,"average_speed":13.02,"average_grade_adjusted_speed":null,"average_heartrate":150.1951219512195,"pace_zone":0},{"distance":1608.5,"elapsed_time":201,"elevation_difference":17,"moving_time":201,"split":5,"average_speed":8,"average_grade_adjusted_speed":null,"average_heartrate":159.09950248756218,"pace_zone":0},{"distance":1618.7,"elapsed_time":164,"elevation_difference":-20.8,"moving_time":164,"split":6,"average_speed":9.87,"average_grade_adjusted_speed":null,"average_heartrate":163.71341463414635,"pace_zone":0},{"distance":1605.7,"elapsed_time":168,"elevation_difference":-0.4,"moving_time":168,"split":7,"average_speed":9.56,"average_grade_adjusted_speed":null,"average_heartrate":165.48214285714286,"pace_zone":0},{"distance":1611.2,"elapsed_time":169,"elevation_difference":-15.6,"moving_time":169,"split":8,"average_speed":9.53,"average_grade_adjusted_speed":null,"average_heartrate":159.01775147928993,"pace_zone":0},{"distance":1603.9,"elapsed_time":165,"elevation_difference":-1.6,"moving_time":165,"split":9,"average_speed":9.72,"average_grade_adjusted_speed":null,"average_heartrate":156.3151515151515,"pace_zone":0},{"distance":1612.7,"elapsed_time":186,"elevation_difference":10.6,"moving_time":186,"split":10,"average_speed":8.67,"average_grade_adjusted_speed":null,"average_heartrate":160.8978494623656,"pace_zone":0},{"distance":1614.5,"elapsed_time":175,"elevation_difference":-1.6,"moving_time":175,"split":11,"average_speed":9.23,"average_grade_adjusted_speed":null,"average_heartrate":162.36,"pace_zone":0},{"distance":1606.1,"elapsed_time":138,"elevation_difference":-24.2,"moving_time":138,"split":12,"average_speed":11.64,"average_grade_adjusted_speed":null,"average_heartrate":160.65942028985506,"pace_zone":0},{"distance":1604.2,"elapsed_time":302,"elevation_difference":49,"moving_time":302,"split":13,"average_speed":5.31,"average_grade_adjusted_speed":null,"average_heartrate":160.3774834437086,"pace_zone":0},{"distance":1611.6,"elapsed_time":188,"elevation_difference":7.6,"moving_time":188,"split":14,"average_speed":8.57,"average_grade_adjusted_speed":null,"average_heartrate":169.46808510638297,"pace_zone":0},{"distance":1609.2,"elapsed_time":140,"elevation_difference":-26.2,"moving_time":140,"split":15,"average_speed":11.49,"average_grade_adjusted_speed":null,"average_heartrate":165.74285714285713,"pace_zone":0},{"distance":1611.1,"elapsed_time":393,"elevation_difference":76,"moving_time":393,"split":16,"average_speed":4.1,"average_grade_adjusted_speed":null,"average_heartrate":158.01272264631044,"pace_zone":0},{"distance":1612.2,"elapsed_time":165,"elevation_difference":-47.8,"moving_time":165,"split":17,"average_speed":9.77,"average_grade_adjusted_speed":null,"average_heartrate":163.27878787878788,"pace_zone":0},{"distance":1606,"elapsed_time":138,"elevation_difference":-38,"moving_time":138,"split":18,"average_speed":11.64,"average_grade_adjusted_speed":null,"average_heartrate":165.231884057971,"pace_zone":0},{"distance":1610,"elapsed_time":205,"elevation_difference":12.4,"moving_time":205,"split":19,"average_speed":7.85,"average_grade_adjusted_speed":null,"average_heartrate":160.73658536585367,"pace_zone":0},{"distance":1607.2,"elapsed_time":153,"elevation_difference":-13.2,"moving_time":153,"split":20,"average_speed":10.5,"average_grade_adjusted_speed":null,"average_heartrate":154.92156862745097,"pace_zone":0},{"distance":1609.7,"elapsed_time":193,"elevation_difference":12.6,"moving_time":193,"split":21,"average_speed":8.34,"average_grade_adjusted_speed":null,"average_heartrate":159.1917098445596,"pace_zone":0},{"distance":1605.5,"elapsed_time":154,"elevation_difference":-13.2,"moving_time":154,"split":22,"average_speed":10.43,"average_grade_adjusted_speed":null,"average_heartrate":156.4805194805195,"pace_zone":0},{"distance":1610,"elapsed_time":202,"elevation_difference":19.4,"moving_time":202,"split":23,"average_speed":7.97,"average_grade_adjusted_speed":null,"average_heartrate":162.02475247524754,"pace_zone":0},{"distance":1612.3,"elapsed_time":398,"elevation_difference":85.8,"moving_time":398,"split":24,"average_speed":4.05,"average_grade_adjusted_speed":null,"average_heartrate":158.76381909547737,"pace_zone":0},{"distance":1614.2,"elapsed_time":99,"elevation_difference":-88.4,"moving_time":99,"split":25,"average_speed":16.31,"average_grade_adjusted_speed":null,"average_heartrate":168.33333333333334,"pace_zone":0},{"distance":1233.2,"elapsed_time":202,"elevation_difference":7.2,"moving_time":202,"split":26,"average_speed":6.1,"average_grade_adjusted_speed":null,"average_heartrate":131.785,"pace_zone":0}],"laps":[{"id":32258696505,"resource_state":2,"name":"Lap 1","activity":{"id":9450997559,"resource_state":1},"athlete":{"id":62214940,"resource_state":1},"elapsed_time":298,"moving_time":299,"start_date":"2023-07-14T16:14:27Z","start_date_local":"2023-07-14T18:14:27Z","distance":2128.3,"start_index":0,"end_index":274,"total_elevation_gain":14.2,"average_speed":7.12,"max_speed":13.538,"average_cadence":92.3,"device_watts":true,"average_watts":92.8,"average_heartrate":116.6,"max_heartrate":127,"lap_index":1,"split":1},{"id":32258696507,"resource_state":2,"name":"Lap 2","activity":{"id":9450997559,"resource_state":1},"athlete":{"id":62214940,"resource_state":1},"elapsed_time":299,"moving_time":300,"start_date":"2023-07-14T16:19:25Z","start_date_local":"2023-07-14T18:19:25Z","distance":1055.4,"start_index":275,"end_index":574,"total_elevation_gain":45.8,"average_speed":3.52,"max_speed":9.8,"average_cadence":93.4,"device_watts":true,"average_watts":135,"average_heartrate":134.9,"max_heartrate":140,"lap_index":2,"split":2},{"id":32258696508,"resource_state":2,"name":"Lap 3","activity":{"id":9450997559,"resource_state":1},"athlete":{"id":62214940,"resource_state":1},"elapsed_time":179,"moving_time":180,"start_date":"2023-07-14T16:24:25Z","start_date_local":"2023-07-14T18:24:25Z","distance":619.07,"start_index":575,"end_index":754,"total_elevation_gain":38,"average_speed":3.44,"max_speed":7.988,"average_cadence":100.2,"device_watts":true,"average_watts":164.7,"average_heartrate":151,"max_heartrate":156,"lap_index":3,"split":3},{"id":32258696512,"resource_state":2,"name":"Lap 4","activity":{"id":9450997559,"resource_state":1},"athlete":{"id":62214940,"resource_state":1},"elapsed_time":119,"moving_time":120,"start_date":"2023-07-14T16:27:25Z","start_date_local":"2023-07-14T18:27:25Z","distance":245.52,"start_index":755,"end_index":874,"total_elevation_gain":19.4,"average_speed":2.05,"max_speed":5.486,"average_cadence":90.2,"device_watts":true,"average_watts":125.5,"average_heartrate":141.1,"max_heartrate":156,"lap_index":4,"split":4},{"id":32258696513,"resource_state":2,"name":"Lap 5","activity":{"id":9450997559,"resource_state":1},"athlete":{"id":62214940,"resource_state":1},"elapsed_time":29,"moving_time":30,"start_date":"2023-07-14T16:29:25Z","start_date_local":"2023-07-14T18:29:25Z","distance":87.7,"start_index":875,"end_index":904,"total_elevation_gain":7,"average_speed":2.92,"max_speed":4.118,"average_cadence":97.6,"device_watts":true,"average_watts":218.4,"average_heartrate":142.8,"max_heartrate":153,"lap_index":5,"split":5},{"id":32258696514,"resource_state":2,"name":"Lap 6","activity":{"id":9450997559,"resource_state":1},"athlete":{"id":62214940,"resource_state":1},"elapsed_time":29,"moving_time":30,"start_date":"2023-07-14T16:29:55Z","start_date_local":"2023-07-14T18:29:55Z","distance":254.25,"start_index":905,"end_index":934,"total_elevation_gain":0,"average_speed":8.48,"max_speed":11.02,"average_cadence":107.3,"device_watts":true,"average_watts":286.3,"average_heartrate":163.4,"max_heartrate":169,"lap_index":6,"split":6},{"id":32258696516,"resource_state":2,"name":"Lap 7","activity":{"id":9450997559,"resource_state":1},"athlete":{"id":62214940,"resource_state":1},"elapsed_time":14,"moving_time":15,"start_date":"2023-07-14T16:30:25Z","start_date_local":"2023-07-14T18:30:25Z","distance":248.08,"start_index":935,"end_index":949,"total_elevation_gain":0,"average_speed":16.54,"max_speed":17.818,"average_cadence":111.9,"device_watts":true,"average_watts":328.7,"average_heartrate":171.3,"max_heartrate":174,"lap_index":7,"split":7},{"id":32258696520,"resource_state":2,"name":"Lap 8","activity":{"id":9450997559,"resource_state":1},"athlete":{"id":62214940,"resource_state":1},"elapsed_time":119,"moving_time":120,"start_date":"2023-07-14T16:30:40Z","start_date_local":"2023-07-14T18:30:40Z","distance":1695.67,"start_index":950,"end_index":1069,"total_elevation_gain":9.6,"average_speed":14.13,"max_speed":20.332,"average_cadence":86.9,"device_watts":true,"average_watts":128.3,"average_heartrate":154.6,"max_heartrate":176,"lap_index":8,"split":8},{"id":32258696526,"resource_state":2,"name":"Lap 9","activity":{"id":9450997559,"resource_state":1},"athlete":{"id":62214940,"resource_state":1},"elapsed_time":599,"moving_time":600,"start_date":"2023-07-14T16:32:40Z","start_date_local":"2023-07-14T18:32:40Z","distance":5344.14,"start_index":1070,"end_index":1669,"total_elevation_gain":72.6,"average_speed":8.91,"max_speed":16.41,"average_cadence":92.2,"device_watts":true,"average_watts":199.8,"average_heartrate":162.1,"max_heartrate":168,"lap_index":9,"split":9},{"id":32258696528,"resource_state":2,"name":"Lap 10","activity":{"id":9450997559,"resource_state":1},"athlete":{"id":62214940,"resource_state":1},"elapsed_time":119,"moving_time":120,"start_date":"2023-07-14T16:42:40Z","start_date_local":"2023-07-14T18:42:40Z","distance":1228.74,"start_index":1670,"end_index":1789,"total_elevation_gain":8.4,"average_speed":10.24,"max_speed":14.016,"average_cadence":86.4,"device_watts":true,"average_watts":150.9,"average_heartrate":156.4,"max_heartrate":163,"lap_index":10,"split":10},{"id":32258696536,"resource_state":2,"name":"Lap 11","activity":{"id":9450997559,"resource_state":1},"athlete":{"id":62214940,"resource_state":1},"elapsed_time":599,"moving_time":600,"start_date":"2023-07-14T16:44:40Z","start_date_local":"2023-07-14T18:44:40Z","distance":5659.08,"start_index":1790,"end_index":2389,"total_elevation_gain":50.8,"average_speed":9.43,"max_speed":14.41,"average_cadence":76,"device_watts":true,"average_watts":199.8,"average_heartrate":160.2,"max_heartrate":164,"lap_index":11,"split":11},{"id":32258696538,"resource_state":2,"name":"Lap 12","activity":{"id":9450997559,"resource_state":1},"athlete":{"id":62214940,"resource_state":1},"elapsed_time":119,"moving_time":120,"start_date":"2023-07-14T16:54:40Z","start_date_local":"2023-07-14T18:54:40Z","distance":961.62,"start_index":2390,"end_index":2509,"total_elevation_gain":15.4,"average_speed":8.01,"max_speed":16.554,"average_cadence":83.9,"device_watts":true,"average_watts":151.1,"average_heartrate":156.3,"max_heartrate":162,"lap_index":12,"split":12},{"id":32258696541,"resource_state":2,"name":"Lap 13","activity":{"id":9450997559,"resource_state":1},"athlete":{"id":62214940,"resource_state":1},"elapsed_time":199,"moving_time":200,"start_date":"2023-07-14T16:56:40Z","start_date_local":"2023-07-14T18:56:40Z","distance":1187,"start_index":2510,"end_index":2709,"total_elevation_gain":39,"average_speed":5.94,"max_speed":13.636,"average_cadence":90.2,"device_watts":true,"average_watts":199.5,"average_heartrate":161.1,"max_heartrate":166,"lap_index":13,"split":13},{"id":32258696543,"resource_state":2,"name":"Lap 14","activity":{"id":9450997559,"resource_state":1},"athlete":{"id":62214940,"resource_state":1},"elapsed_time":199,"moving_time":200,"start_date":"2023-07-14T17:00:00Z","start_date_local":"2023-07-14T19:00:00Z","distance":1684.2,"start_index":2710,"end_index":2909,"total_elevation_gain":26.6,"average_speed":8.42,"max_speed":14.532,"average_cadence":104.8,"device_watts":true,"average_watts":200.1,"average_heartrate":169.1,"max_heartrate":171,"lap_index":14,"split":14},{"id":32258696547,"resource_state":2,"name":"Lap 15","activity":{"id":9450997559,"resource_state":1},"athlete":{"id":62214940,"resource_state":1},"elapsed_time":199,"moving_time":200,"start_date":"2023-07-14T17:03:20Z","start_date_local":"2023-07-14T19:03:20Z","distance":1991.89,"start_index":2910,"end_index":3109,"total_elevation_gain":12.2,"average_speed":9.96,"max_speed":14.658,"average_cadence":92.1,"device_watts":true,"average_watts":199.9,"average_heartrate":166,"max_heartrate":170,"lap_index":15,"split":15},{"id":32258696549,"resource_state":2,"name":"Lap 16","activity":{"id":9450997559,"resource_state":1},"athlete":{"id":62214940,"resource_state":1},"elapsed_time":119,"moving_time":120,"start_date":"2023-07-14T17:06:40Z","start_date_local":"2023-07-14T19:06:40Z","distance":498.34,"start_index":3110,"end_index":3229,"total_elevation_gain":23,"average_speed":4.15,"max_speed":10.926,"average_cadence":86.1,"device_watts":true,"average_watts":150.9,"average_heartrate":158.3,"max_heartrate":166,"lap_index":16,"split":16},{"id":32258696553,"resource_state":2,"name":"Lap 17","activity":{"id":9450997559,"resource_state":1},"athlete":{"id":62214940,"resource_state":1},"elapsed_time":29,"moving_time":30,"start_date":"2023-07-14T17:08:40Z","start_date_local":"2023-07-14T19:08:40Z","distance":171.05,"start_index":3230,"end_index":3259,"total_elevation_gain":2.4,"average_speed":5.7,"max_speed":8.962,"average_cadence":98.9,"device_watts":true,"average_watts":220.6,"average_heartrate":154.6,"max_heartrate":161,"lap_index":17,"split":17},{"id":32258696554,"resource_state":2,"name":"Lap 18","activity":{"id":9450997559,"resource_state":1},"athlete":{"id":62214940,"resource_state":1},"elapsed_time":29,"moving_time":30,"start_date":"2023-07-14T17:09:10Z","start_date_local":"2023-07-14T19:09:10Z","distance":139.3,"start_index":3260,"end_index":3289,"total_elevation_gain":13.6,"average_speed":4.64,"max_speed":9.198,"average_cadence":108,"device_watts":true,"average_watts":285.6,"average_heartrate":168.1,"max_heartrate":173,"lap_index":18,"split":18},{"id":32258696557,"resource_state":2,"name":"Lap 19","activity":{"id":9450997559,"resource_state":1},"athlete":{"id":62214940,"resource_state":1},"elapsed_time":14,"moving_time":15,"start_date":"2023-07-14T17:09:40Z","start_date_local":"2023-07-14T19:09:40Z","distance":62.18,"start_index":3290,"end_index":3304,"total_elevation_gain":5.8,"average_speed":4.15,"max_speed":4.296,"average_cadence":112.4,"device_watts":true,"average_watts":329.4,"average_heartrate":175.4,"max_heartrate":177,"lap_index":19,"split":19},{"id":32258696558,"resource_state":2,"name":"Lap 20","activity":{"id":9450997559,"resource_state":1},"athlete":{"id":62214940,"resource_state":1},"elapsed_time":119,"moving_time":120,"start_date":"2023-07-14T17:09:55Z","start_date_local":"2023-07-14T19:09:55Z","distance":176.74,"start_index":3305,"end_index":3424,"total_elevation_gain":21.2,"average_speed":1.47,"max_speed":4.144,"average_cadence":87.5,"device_watts":true,"average_watts":128.3,"average_heartrate":157,"max_heartrate":179,"lap_index":20,"split":20},{"id":32258696563,"resource_state":2,"name":"Lap 21","activity":{"id":9450997559,"resource_state":1},"athlete":{"id":62214940,"resource_state":1},"elapsed_time":299,"moving_time":300,"start_date":"2023-07-14T17:11:55Z","start_date_local":"2023-07-14T19:11:55Z","distance":3144.44,"start_index":3425,"end_index":3724,"total_elevation_gain":30.2,"average_speed":10.48,"max_speed":19.06,"average_cadence":90.9,"device_watts":true,"average_watts":209.5,"average_heartrate":161.2,"max_heartrate":167,"lap_index":21,"split":21},{"id":32258696566,"resource_state":2,"name":"Lap 22","activity":{"id":9450997559,"resource_state":1},"athlete":{"id":62214940,"resource_state":1},"elapsed_time":299,"moving_time":300,"start_date":"2023-07-14T17:16:55Z","start_date_local":"2023-07-14T19:16:55Z","distance":2383.61,"start_index":3725,"end_index":4024,"total_elevation_gain":43,"average_speed":7.95,"max_speed":13.712,"average_cadence":91.5,"device_watts":true,"average_watts":190.2,"average_heartrate":161.3,"max_heartrate":166,"lap_index":22,"split":22},{"id":32258696570,"resource_state":2,"name":"Lap 23","activity":{"id":9450997559,"resource_state":1},"athlete":{"id":62214940,"resource_state":1},"elapsed_time":119,"moving_time":120,"start_date":"2023-07-14T17:21:55Z","start_date_local":"2023-07-14T19:21:55Z","distance":1264.53,"start_index":4025,"end_index":4144,"total_elevation_gain":7.6,"average_speed":10.54,"max_speed":13.69,"average_cadence":86.5,"device_watts":true,"average_watts":150.7,"average_heartrate":152.5,"max_heartrate":161,"lap_index":23,"split":23},{"id":32258696572,"resource_state":2,"name":"Lap 24","activity":{"id":9450997559,"resource_state":1},"athlete":{"id":62214940,"resource_state":1},"elapsed_time":149,"moving_time":150,"start_date":"2023-07-14T17:23:55Z","start_date_local":"2023-07-14T19:23:55Z","distance":1233.08,"start_index":4145,"end_index":4294,"total_elevation_gain":16,"average_speed":8.22,"max_speed":11.108,"average_cadence":99.7,"device_watts":true,"average_watts":209.4,"average_heartrate":159.4,"max_heartrate":166,"lap_index":24,"split":24},{"id":32258696576,"resource_state":2,"name":"Lap 25","activity":{"id":9450997559,"resource_state":1},"athlete":{"id":62214940,"resource_state":1},"elapsed_time":149,"moving_time":150,"start_date":"2023-07-14T17:26:25Z","start_date_local":"2023-07-14T19:26:25Z","distance":1664.49,"start_index":4295,"end_index":4444,"total_elevation_gain":6.2,"average_speed":11.1,"max_speed":15.252,"average_cadence":81.7,"device_watts":true,"average_watts":190,"average_heartrate":156.9,"max_heartrate":164,"lap_index":25,"split":25},{"id":32258696577,"resource_state":2,"name":"Lap 26","activity":{"id":9450997559,"resource_state":1},"athlete":{"id":62214940,"resource_state":1},"elapsed_time":149,"moving_time":150,"start_date":"2023-07-14T17:28:55Z","start_date_local":"2023-07-14T19:28:55Z","distance":1472.22,"start_index":4445,"end_index":4594,"total_elevation_gain":10.4,"average_speed":9.81,"max_speed":12.859,"average_cadence":99.3,"device_watts":true,"average_watts":210,"average_heartrate":163.6,"max_heartrate":166,"lap_index":26,"split":26},{"id":32258696582,"resource_state":2,"name":"Lap 27","activity":{"id":9450997559,"resource_state":1},"athlete":{"id":62214940,"resource_state":1},"elapsed_time":149,"moving_time":150,"start_date":"2023-07-14T17:31:25Z","start_date_local":"2023-07-14T19:31:25Z","distance":595.84,"start_index":4595,"end_index":4744,"total_elevation_gain":36.6,"average_speed":3.97,"max_speed":9.222,"average_cadence":82.2,"device_watts":true,"average_watts":190.1,"average_heartrate":156.6,"max_heartrate":166,"lap_index":27,"split":27},{"id":32258696585,"resource_state":2,"name":"Lap 28","activity":{"id":9450997559,"resource_state":1},"athlete":{"id":62214940,"resource_state":1},"elapsed_time":149,"moving_time":150,"start_date":"2023-07-14T17:33:55Z","start_date_local":"2023-07-14T19:33:55Z","distance":683.32,"start_index":4745,"end_index":4894,"total_elevation_gain":32.2,"average_speed":4.56,"max_speed":9.404,"average_cadence":99.1,"device_watts":true,"average_watts":210,"average_heartrate":162,"max_heartrate":165,"lap_index":28,"split":28},{"id":32258696591,"resource_state":2,"name":"Lap 29","activity":{"id":9450997559,"resource_state":1},"athlete":{"id":62214940,"resource_state":1},"elapsed_time":149,"moving_time":150,"start_date":"2023-07-14T17:36:25Z","start_date_local":"2023-07-14T19:36:25Z","distance":495.45,"start_index":4895,"end_index":5044,"total_elevation_gain":36.8,"average_speed":3.3,"max_speed":7.884,"average_cadence":82.5,"device_watts":true,"average_watts":190.1,"average_heartrate":157.3,"max_heartrate":163,"lap_index":29,"split":29},{"id":32258696592,"resource_state":2,"name":"Lap 30","activity":{"id":9450997559,"resource_state":1},"athlete":{"id":62214940,"resource_state":1},"elapsed_time":29,"moving_time":30,"start_date":"2023-07-14T17:38:55Z","start_date_local":"2023-07-14T19:38:55Z","distance":176.89,"start_index":5045,"end_index":5074,"total_elevation_gain":3.2,"average_speed":5.9,"max_speed":8.116,"average_cadence":96.8,"device_watts":true,"average_watts":223.4,"average_heartrate":158,"max_heartrate":163,"lap_index":30,"split":30},{"id":32258696594,"resource_state":2,"name":"Lap 31","activity":{"id":9450997559,"resource_state":1},"athlete":{"id":62214940,"resource_state":1},"elapsed_time":29,"moving_time":30,"start_date":"2023-07-14T17:39:25Z","start_date_local":"2023-07-14T19:39:25Z","distance":419.28,"start_index":5075,"end_index":5104,"total_elevation_gain":0,"average_speed":13.98,"max_speed":17.564,"average_cadence":108.1,"device_watts":true,"average_watts":286,"average_heartrate":167.8,"max_heartrate":171,"lap_index":31,"split":31},{"id":32258696597,"resource_state":2,"name":"Lap 32","activity":{"id":9450997559,"resource_state":1},"athlete":{"id":62214940,"resource_state":1},"elapsed_time":14,"moving_time":15,"start_date":"2023-07-14T17:39:55Z","start_date_local":"2023-07-14T19:39:55Z","distance":221.87,"start_index":5105,"end_index":5119,"total_elevation_gain":0,"average_speed":14.79,"max_speed":16.455,"average_cadence":112.7,"device_watts":true,"average_watts":329.1,"average_heartrate":171.8,"max_heartrate":174,"lap_index":32,"split":32},{"id":32258696603,"resource_state":2,"name":"Lap 33","activity":{"id":9450997559,"resource_state":1},"athlete":{"id":62214940,"resource_state":1},"elapsed_time":254,"moving_time":255,"start_date":"2023-07-14T17:40:10Z","start_date_local":"2023-07-14T19:40:10Z","distance":2273.9,"start_index":5120,"end_index":5334,"total_elevation_gain":17.2,"average_speed":8.92,"max_speed":20.688,"average_cadence":89.6,"device_watts":true,"average_watts":99.4,"average_heartrate":140.8,"max_heartrate":175,"lap_index":33,"split":33},{"id":32258696605,"resource_state":2,"name":"Lap 34","activity":{"id":9450997559,"resource_state":1},"athlete":{"id":62214940,"resource_state":1},"elapsed_time":8,"moving_time":9,"start_date":"2023-07-14T17:44:25Z","start_date_local":"2023-07-14T19:44:25Z","distance":8.81,"start_index":5334,"end_index":5334,"total_elevation_gain":0,"average_speed":0.98,"max_speed":1.45,"average_cadence":87.8,"device_watts":true,"average_watts":46,"average_heartrate":121.1,"max_heartrate":122,"lap_index":34,"split":34}],"gear":{"id":"b12659743","primary":false,"name":"Zwift Hub","nickname":"Zwift Hub","resource_state":2,"retired":false,"distance":907512,"converted_distance":907.5},"photos":{"primary":{"unique_id":"80f16acc-7607-487f-abf0-dad5767e839c","urls":{"600":"https:\/\/dgtzuqphqg23d.cloudfront.net\/sgfv6aXVczf-nMyMsFF-zJXi8BL6KzZGt7e-sQJdj7A-768x432.jpg","100":"https:\/\/dgtzuqphqg23d.cloudfront.net\/sgfv6aXVczf-nMyMsFF-zJXi8BL6KzZGt7e-sQJdj7A-128x72.jpg"},"source":1,"media_type":1},"use_primary_photo":true,"count":4},"stats_visibility":[{"type":"heart_rate","visibility":"everyone"},{"type":"pace","visibility":"everyone"},{"type":"power","visibility":"everyone"},{"type":"speed","visibility":"everyone"},{"type":"calories","visibility":"everyone"}],"hide_from_home":false,"device_name":"Zwift","embed_token":"338976646c142f89955cb25115642930eee2b424","available_zones":[],"start_date_timestamp":1689351267,"_id":100,"athlete_weight":69,"localImagePaths":["files\/activities\/b9e80518-53a7-11ee-8800-9a34a3268d74.jpg","files\/activities\/b9f0c19e-53a7-11ee-9acd-9a34a3268d74.jpg","files\/activities\/b9f87312-53a7-11ee-af2b-9a34a3268d74.jpg","files\/activities\/b9fe724e-53a7-11ee-8fbf-9a34a3268d74.jpg"]}