{"resource_state":3,"athlete":{"id":62214940,"resource_state":1},"name":"Zwift - Pedaling Drills in Makuri Islands","distance":8190.1,"moving_time":1221,"elapsed_time":1221,"total_elevation_gain":79,"type":"VirtualRide","sport_type":"VirtualRide","id":9138442860,"start_date":"2023-05-25T14:58:10Z","start_date_local":"2023-05-25T16:58:10Z","timezone":"(GMT+01:00) Europe\/Brussels","utc_offset":7200,"location_city":null,"location_state":null,"location_country":null,"achievement_count":4,"kudos_count":2,"comment_count":0,"athlete_count":1,"photo_count":0,"map":{"id":"a9138442860","polyline":"~m{`Auu`s^OIUSQWMWIYIe@?QDYJYT[\\a@\\[jAo@^OVEX?n@Ln@Z\\\\LVDXAlABVBHNNNJXFbBNXDXHRNJNLZNzAJd@FHTNXFV@fAAz@E\\Gr@e@PQHOBM@WCYI]KYQUSKWE]?YF]L[TMPIZAj@Dx@ZdCTpAZnCNn@L`@P\\JNNHRFf@@~BMj@?TBRFPNHRDTFl@O`EIf@KNOJQDQ@e@?a@MMKS]MMMG]Em@C]Bk@L]LeB`Aa@Lc@HQ@SAOGo@_@SCQ@SFOHKNc@nA_AlAWTMH_@H_@?OEMGg@a@MGQ@_ARO?OC[SKKQ[M_@Ea@Aa@@QDOJKXQzAa@`@QNOFUAKEKSS]OgA_@OKOMIQGQAi@EQg@k@ES@SDQRa@V[X[j@e@NIPEP?PBv@h@N@NEd@[ZEL@TJHHLVFd@HhAFTFFX@VC`@O\\UZYT_@LWF[B]G]GO[Ua@MgCc@c@UMMCUBSVw@@QAa@GOSW]a@a@[e@W[G[Du@T[B[K_@[QWMYMg@C[?OHYTc@f@m@ZWh@]x@_@VIZAXDf@Ll@^RRLXDf@AjAFTFHNJVJ~BRVHVLRVJZPbBFXPPTJVD`B?fAILE^U`@_@JQBSA_@EYGWMWMMSKSEW?]DWH]PQPKRETA`@Fz@ZdCVzAVbCNr@Xr@V^PJRBj@@nBKl@AVBTFPNHTFVDn@AVOrDGTIPOJSDS@g@AQEOIMMU_@MIOEo@Eq@@]F_@LuBhAa@La@FQ@SAOGm@_@SCc@HOHKLe@pASXw@`A[RODa@@OA]Og@_@OEO@o@POBQAOEMIWWWm@Iq@Ac@BOHOXSdBg@XKRUDK@OEMWUeBq@QKMOIQEQCg@ESg@k@CQ@SNa@`@m@t@q@","resource_state":3,"summary_polyline":"~m{`Auu`s^OIUSQWMWIYIe@?QDYJYT[\\a@\\[jAo@^OVEX?n@Ln@Z\\\\LVDXAlABVBHNNNJXFbBNXDXHRNJNLZNzAJd@FHTNXFV@fAAz@E\\Gr@e@PQHOBM@WCYI]KYQUWMWC]@UD]L[TMPIZAj@Dx@ZdCTpAZnCNn@L`@P\\JNNHRFf@@~BMj@?TBRFPNHRDTFl@O`EIf@KNOJQDQ@e@?a@MMKS]MMMG]Em@C]Bk@L]LeB`Aa@Lc@HQ@SAOGo@_@SCQ@SFOHKNc@nA_AlAWTMH_@H_@?OEMGg@a@MGQ@_ARO?OC[SKKQ[M_@Ea@Aa@@QDOJKXQzAa@`@QNOFUAKEKSS]OgA_@OKOMIQGQAi@EQg@k@ES@SDQRa@V[X[j@e@NIPEP?PBv@h@N@NEd@[ZEL@TJHHLVFd@HhAFTFFX@VC`@O\\UZYT_@LWF[B]G]GO[Ua@MgCc@c@UMMCUBSVw@@QAa@GOSW]a@a@[e@W[G[Du@T[B[K_@[QWMYMg@C[?OHYTc@f@m@ZWh@]x@_@VIZAXDf@Ll@^RRLXDf@AjAFTFHNJVJ~BRVHVLRVJZPbBFXPPTJVD`B?fAILE^U`@_@JQBSA_@EYGWMWMMSKSEW?]DWH]PQPKRETA`@Fz@ZdCVzAVbCNr@Xr@V^PJRBj@@nBKl@AVBTFPNHTFVDn@AVOrDGTIPOJSDS@g@AQEOIMMU_@MIOEo@Eq@@]F_@LuBhAa@La@FQ@SAOGm@_@SCc@HOHKLe@pASXw@`A[RODa@@OA]Og@_@OEO@o@POBQAOEMIWWWm@Iq@Ac@BOHOXSdBg@XKRUDK@OEMWUeBq@QKMOIQEQCg@ESg@k@CQ@SNa@`@m@t@q@"},"trainer":false,"commute":false,"manual":false,"private":false,"visibility":"everyone","flagged":false,"gear_id":"b12659792","start_latlng":[-10.8,165.81],"end_latlng":[-10.8,165.81],"average_speed":6.708,"max_speed":13.386,"average_cadence":87.8,"average_watts":148.4,"max_watts":421,"weighted_average_watts":155,"kilojoules":181.3,"device_watts":true,"has_heartrate":true,"average_heartrate":156.3,"max_heartrate":179,"heartrate_opt_out":false,"display_hide_heartrate_option":true,"elev_high":25.6,"elev_low":3.6,"upload_id":9804870421,"upload_id_str":"9804870421","external_id":"zwift-activity-1351555757434224672.fit","from_accepted_tag":false,"pr_count":2,"total_photo_count":4,"has_kudoed":false,"description":null,"calories":173,"perceived_exertion":null,"prefer_perceived_exertion":null,"segment_efforts":[{"id":3096835505875307056,"resource_state":2,"name":"Mech Isle Loop","activity":{"id":9138442860,"resource_state":1},"athlete":{"id":62214940,"resource_state":1},"elapsed_time":638,"moving_time":638,"start_date":"2023-05-25T14:58:15Z","start_date_local":"2023-05-25T16:58:15Z","distance":4021.4,"start_index":0,"end_index":523,"average_cadence":86.6,"device_watts":true,"average_watts":135.6,"average_heartrate":147.8,"max_heartrate":171,"segment":{"id":33214506,"resource_state":2,"name":"Mech Isle Loop","activity_type":"VirtualRide","distance":4021.4,"average_grade":0,"maximum_grade":6.8,"elevation_high":25.6,"elevation_low":3.6,"start_latlng":[-10.796355,165.812767],"end_latlng":[-10.796359,165.812767],"elevation_profile":null,"climb_category":0,"city":"Nemboe","state":"Temotu Province","country":"Solomon Islands","private":false,"hazardous":false,"starred":false},"pr_rank":2,"achievements":[{"type_id":3,"type":"pr","rank":2}],"hidden":false},{"id":3096835505878482480,"resource_state":2,"name":"Mech Isle Climb CW","activity":{"id":9138442860,"resource_state":1},"athlete":{"id":62214940,"resource_state":1},"elapsed_time":226,"moving_time":226,"start_date":"2023-05-25T15:01:27Z","start_date_local":"2023-05-25T17:01:27Z","distance":714.5,"start_index":77,"end_index":303,"average_cadence":87.5,"device_watts":true,"average_watts":128.8,"average_heartrate":142.9,"max_heartrate":157,"segment":{"id":33263289,"resource_state":2,"name":"Mech Isle Climb CW","activity_type":"VirtualRide","distance":714.5,"average_grade":2.9,"maximum_grade":6.7,"elevation_high":25.4,"elevation_low":4.4,"start_latlng":[-10.796924,165.815588],"end_latlng":[-10.798919,165.814322],"elevation_profile":null,"climb_category":0,"city":"Nemboe","state":"Temotu Province","country":"Solomon Islands","private":false,"hazardous":false,"starred":false},"pr_rank":2,"achievements":[{"type_id":3,"type":"pr","rank":2}],"hidden":false},{"id":3096835505877277232,"resource_state":2,"name":"Mech Isle Loop","activity":{"id":9138442860,"resource_state":1},"athlete":{"id":62214940,"resource_state":1},"elapsed_time":558,"moving_time":558,"start_date":"2023-05-25T15:08:53Z","start_date_local":"2023-05-25T17:08:53Z","distance":4021.4,"start_index":523,"end_index":1068,"average_cadence":89.8,"device_watts":true,"average_watts":165.1,"average_heartrate":165.7,"max_heartrate":179,"segment":{"id":33214506,"resource_state":2,"name":"Mech Isle Loop","activity_type":"VirtualRide","distance":4021.4,"average_grade":0,"maximum_grade":6.8,"elevation_high":25.6,"elevation_low":3.6,"start_latlng":[-10.796355,165.812767],"end_latlng":[-10.796359,165.812767],"elevation_profile":null,"climb_category":0,"city":"Nemboe","state":"Temotu Province","country":"Solomon Islands","private":false,"hazardous":false,"starred":false},"pr_rank":1,"achievements":[{"type_id":3,"type":"pr","rank":1}],"hidden":false},{"id":3096835505875611184,"resource_state":2,"name":"Mech Isle Climb CW","activity":{"id":9138442860,"resource_state":1},"athlete":{"id":62214940,"resource_state":1},"elapsed_time":194,"moving_time":194,"start_date":"2023-05-25T15:11:27Z","start_date_local":"2023-05-25T17:11:27Z","distance":714.5,"start_index":677,"end_index":871,"average_cadence":86.3,"device_watts":true,"average_watts":154,"average_heartrate":155.6,"max_heartrate":177,"segment":{"id":33263289,"resource_state":2,"name":"Mech Isle Climb CW","activity_type":"VirtualRide","distance":714.5,"average_grade":2.9,"maximum_grade":6.7,"elevation_high":25.4,"elevation_low":4.4,"start_latlng":[-10.796924,165.815588],"end_latlng":[-10.798919,165.814322],"elevation_profile":null,"climb_category":0,"city":"Nemboe","state":"Temotu Province","country":"Solomon Islands","private":false,"hazardous":false,"starred":false},"pr_rank":1,"achievements":[{"type_id":3,"type":"pr","rank":1}],"hidden":false}],"splits_metric":[{"distance":1001.3,"elapsed_time":161,"elevation_difference":-0.2,"moving_time":161,"split":1,"average_speed":6.22,"average_grade_adjusted_speed":null,"average_heartrate":139.0248447204969,"pace_zone":0},{"distance":1003.4,"elapsed_time":269,"elevation_difference":20.2,"moving_time":269,"split":2,"average_speed":3.73,"average_grade_adjusted_speed":null,"average_heartrate":142.26765799256506,"pace_zone":0},{"distance":997.9,"elapsed_time":102,"elevation_difference":-21.2,"moving_time":102,"split":3,"average_speed":9.78,"average_grade_adjusted_speed":null,"average_heartrate":157.9607843137255,"pace_zone":0},{"distance":1004.8,"elapsed_time":106,"elevation_difference":0.8,"moving_time":106,"split":4,"average_speed":9.48,"average_grade_adjusted_speed":null,"average_heartrate":162.73584905660377,"pace_zone":0},{"distance":995.4,"elapsed_time":120,"elevation_difference":0.2,"moving_time":120,"split":5,"average_speed":8.3,"average_grade_adjusted_speed":null,"average_heartrate":168.6,"pace_zone":0},{"distance":998.1,"elapsed_time":232,"elevation_difference":20.4,"moving_time":232,"split":6,"average_speed":4.3,"average_grade_adjusted_speed":null,"average_heartrate":158.38362068965517,"pace_zone":0},{"distance":1005.7,"elapsed_time":100,"elevation_difference":-20.6,"moving_time":100,"split":7,"average_speed":10.06,"average_grade_adjusted_speed":null,"average_heartrate":175.55,"pace_zone":0},{"distance":994.4,"elapsed_time":102,"elevation_difference":0,"moving_time":102,"split":8,"average_speed":9.75,"average_grade_adjusted_speed":null,"average_heartrate":168.72549019607843,"pace_zone":0},{"distance":191.1,"elapsed_time":29,"elevation_difference":2.6,"moving_time":29,"split":9,"average_speed":6.59,"average_grade_adjusted_speed":null,"average_heartrate":175.53846153846155,"pace_zone":0}],"splits_standard":[{"distance":1611.9,"elapsed_time":277,"elevation_difference":4.8,"moving_time":277,"split":1,"average_speed":5.82,"average_grade_adjusted_speed":null,"average_heartrate":138.30685920577616,"pace_zone":0},{"distance":1614.7,"elapsed_time":278,"elevation_difference":-5,"moving_time":278,"split":2,"average_speed":5.81,"average_grade_adjusted_speed":null,"average_heartrate":151.54676258992805,"pace_zone":0},{"distance":1608.3,"elapsed_time":181,"elevation_difference":0,"moving_time":181,"split":3,"average_speed":8.89,"average_grade_adjusted_speed":null,"average_heartrate":165.73480662983425,"pace_zone":0},{"distance":1611.9,"elapsed_time":302,"elevation_difference":4.8,"moving_time":302,"split":4,"average_speed":5.34,"average_grade_adjusted_speed":null,"average_heartrate":162.4933774834437,"pace_zone":0},{"distance":1604.2,"elapsed_time":159,"elevation_difference":-5,"moving_time":159,"split":5,"average_speed":10.09,"average_grade_adjusted_speed":null,"average_heartrate":170.60377358490567,"pace_zone":0},{"distance":141.1,"elapsed_time":24,"elevation_difference":2.6,"moving_time":24,"split":6,"average_speed":5.88,"average_grade_adjusted_speed":null,"average_heartrate":175.38095238095238,"pace_zone":0}],"laps":[{"id":31126382608,"resource_state":2,"name":"Lap 1","activity":{"id":9138442860,"resource_state":1},"athlete":{"id":62214940,"resource_state":1},"elapsed_time":598,"moving_time":599,"start_date":"2023-05-25T14:58:10Z","start_date_local":"2023-05-25T16:58:10Z","distance":3600.17,"start_index":0,"end_index":477,"total_elevation_gain":34.6,"average_speed":6.01,"max_speed":12.76,"average_cadence":85.7,"device_watts":true,"average_watts":134,"average_heartrate":146.1,"max_heartrate":165,"lap_index":1,"split":1},{"id":31126382610,"resource_state":2,"name":"Lap 2","activity":{"id":9138442860,"resource_state":1},"athlete":{"id":62214940,"resource_state":1},"elapsed_time":29,"moving_time":30,"start_date":"2023-05-25T15:08:08Z","start_date_local":"2023-05-25T17:08:08Z","distance":305.32,"start_index":478,"end_index":507,"total_elevation_gain":0,"average_speed":10.18,"max_speed":11.302,"average_cadence":91.6,"device_watts":true,"average_watts":196.1,"average_heartrate":163.7,"max_heartrate":169,"lap_index":2,"split":2},{"id":31126382612,"resource_state":2,"name":"Lap 3","activity":{"id":9138442860,"resource_state":1},"athlete":{"id":62214940,"resource_state":1},"elapsed_time":29,"moving_time":30,"start_date":"2023-05-25T15:08:38Z","start_date_local":"2023-05-25T17:08:38Z","distance":259.27,"start_index":508,"end_index":537,"total_elevation_gain":2.6,"average_speed":8.64,"max_speed":10.576,"average_cadence":88,"device_watts":true,"average_watts":119.2,"average_heartrate":168.5,"max_heartrate":171,"lap_index":3,"split":3},{"id":31126382613,"resource_state":2,"name":"Lap 4","activity":{"id":9138442860,"resource_state":1},"athlete":{"id":62214940,"resource_state":1},"elapsed_time":29,"moving_time":30,"start_date":"2023-05-25T15:09:08Z","start_date_local":"2023-05-25T17:09:08Z","distance":216.67,"start_index":538,"end_index":567,"total_elevation_gain":3.6,"average_speed":7.22,"max_speed":8.208,"average_cadence":103.7,"device_watts":true,"average_watts":217.6,"average_heartrate":166.4,"max_heartrate":171,"lap_index":4,"split":4},{"id":31126382616,"resource_state":2,"name":"Lap 5","activity":{"id":9138442860,"resource_state":1},"athlete":{"id":62214940,"resource_state":1},"elapsed_time":29,"moving_time":30,"start_date":"2023-05-25T15:09:38Z","start_date_local":"2023-05-25T17:09:38Z","distance":307.55,"start_index":568,"end_index":597,"total_elevation_gain":0,"average_speed":10.25,"max_speed":11.75,"average_cadence":90.2,"device_watts":true,"average_watts":114.7,"average_heartrate":170.7,"max_heartrate":173,"lap_index":5,"split":5},{"id":31126382619,"resource_state":2,"name":"Lap 6","activity":{"id":9138442860,"resource_state":1},"athlete":{"id":62214940,"resource_state":1},"elapsed_time":29,"moving_time":30,"start_date":"2023-05-25T15:10:08Z","start_date_local":"2023-05-25T17:10:08Z","distance":241.52,"start_index":598,"end_index":627,"total_elevation_gain":0,"average_speed":8.05,"max_speed":8.332,"average_cadence":110.5,"device_watts":true,"average_watts":238.3,"average_heartrate":167.3,"max_heartrate":173,"lap_index":6,"split":6},{"id":31126382624,"resource_state":2,"name":"Lap 7","activity":{"id":9138442860,"resource_state":1},"athlete":{"id":62214940,"resource_state":1},"elapsed_time":149,"moving_time":150,"start_date":"2023-05-25T15:10:38Z","start_date_local":"2023-05-25T17:10:38Z","distance":755.32,"start_index":628,"end_index":777,"total_elevation_gain":7,"average_speed":5.04,"max_speed":7.95,"average_cadence":87.9,"device_watts":true,"average_watts":115.8,"average_heartrate":156.8,"max_heartrate":176,"lap_index":7,"split":7},{"id":31126382627,"resource_state":2,"name":"Lap 8","activity":{"id":9138442860,"resource_state":1},"athlete":{"id":62214940,"resource_state":1},"elapsed_time":149,"moving_time":150,"start_date":"2023-05-25T15:13:08Z","start_date_local":"2023-05-25T17:13:08Z","distance":892.69,"start_index":778,"end_index":927,"total_elevation_gain":14,"average_speed":5.95,"max_speed":13.386,"average_cadence":84.3,"device_watts":true,"average_watts":193.3,"average_heartrate":168.5,"max_heartrate":179,"lap_index":8,"split":8},{"id":31126382631,"resource_state":2,"name":"Lap 9","activity":{"id":9138442860,"resource_state":1},"athlete":{"id":62214940,"resource_state":1},"elapsed_time":172,"moving_time":173,"start_date":"2023-05-25T15:15:38Z","start_date_local":"2023-05-25T17:15:38Z","distance":1613.62,"start_index":928,"end_index":1068,"total_elevation_gain":10.2,"average_speed":9.33,"max_speed":13.018,"average_cadence":90.3,"device_watts":true,"average_watts":162.2,"average_heartrate":170.7,"max_heartrate":178,"lap_index":9,"split":9}],"photos":{"primary":{"unique_id":"866b41a8-2d96-41ab-ac31-ce25e23fc72b","urls":{"600":"https:\/\/dgtzuqphqg23d.cloudfront.net\/NGQRwffWG8RXHnMb_jjE061OmYbBlnyDE4tWzJIZn2A-768x432.jpg","100":"https:\/\/dgtzuqphqg23d.cloudfront.net\/NGQRwffWG8RXHnMb_jjE061OmYbBlnyDE4tWzJIZn2A-128x72.jpg"},"source":1,"media_type":1},"use_primary_photo":true,"count":4},"stats_visibility":[{"type":"heart_rate","visibility":"everyone"},{"type":"pace","visibility":"everyone"},{"type":"power","visibility":"everyone"},{"type":"speed","visibility":"everyone"},{"type":"calories","visibility":"everyone"}],"hide_from_home":false,"device_name":"Zwift","embed_token":"6c74e0a01faa3acdc86b280aa8c1232f78b39453","available_zones":[],"start_date_timestamp":1685026690,"_id":7,"athlete_weight":69,"localImagePaths":["files\/activities\/032c91a8-53a8-11ee-87d7-9a34a3268d74.jpg","files\/activities\/03b98824-53a8-11ee-8f03-9a34a3268d74.jpg","files\/activities\/043c59ac-53a8-11ee-b96c-9a34a3268d74.jpg","files\/activities\/04b4b618-53a8-11ee-9cd4-9a34a3268d74.jpg"]}